[{"timestamp": 1783209600, "price": 24.98}, {"timestamp": 1783210500, "price": 23.69}, {"timestamp": 1783211400, "price": 22.52}, {"timestamp": 1783212300, "price": 20.91}, {"timestamp": 1783213200, "price": 24.79}, {"timestamp": 1783214100, "price": 23.56}, {"timestamp": 1783215000, "price": 23.08}, {"timestamp": 1783215900, "price": 20.92}, {"timestamp": 1783216800, "price": 22.33}, {"timestamp": 1783217700, "price": 22.01}, {"timestamp": 1783218600, "price": 24.38}, {"timestamp": 1783219500, "price": 23.41}, {"timestamp": 1783220400, "price": 24.49}, {"timestamp": 1783221300, "price": 25.02}, {"timestamp": 1783222200, "price": 28.32}, {"timestamp": 1783223100, "price": 30.63}, {"timestamp": 1783224000, "price": 26.83}, {"timestamp": 1783224900, "price": 28.37}, {"timestamp": 1783225800, "price": 32.01}, {"timestamp": 1783226700, "price": 34.04}, {"timestamp": 1783227600, "price": 43.8}, {"timestamp": 1783228500, "price": 35.65}, {"timestamp": 1783229400, "price": 28.37}, {"timestamp": 1783230300, "price": 17.49}, {"timestamp": 1783231200, "price": 31.83}, {"timestamp": 1783232100, "price": 18.18}, {"timestamp": 1783233000, "price": 7.96}, {"timestamp": 1783233900, "price": 4.94}, {"timestamp": 1783234800, "price": 10.48}, {"timestamp": 1783235700, "price": 9.0}, {"timestamp": 1783236600, "price": 9.0}, {"timestamp": 1783237500, "price": 8.26}, {"timestamp": 1783238400, "price": 11.26}, {"timestamp": 1783239300, "price": 10.52}, {"timestamp": 1783240200, "price": 10.0}, {"timestamp": 1783241100, "price": 9.39}, {"timestamp": 1783242000, "price": 11.51}, {"timestamp": 1783242900, "price": 10.0}, {"timestamp": 1783243800, "price": 9.99}, {"timestamp": 1783244700, "price": 8.42}, {"timestamp": 1783245600, "price": 9.99}, {"timestamp": 1783246500, "price": 8.26}, {"timestamp": 1783247400, "price": 6.05}, {"timestamp": 1783248300, "price": 5.12}, {"timestamp": 1783249200, "price": 4.95}, {"timestamp": 1783250100, "price": 4.69}, {"timestamp": 1783251000, "price": 4.27}, {"timestamp": 1783251900, "price": 3.52}, {"timestamp": 1783252800, "price": 3.26}, {"timestamp": 1783253700, "price": 2.95}, {"timestamp": 1783254600, "price": 2.73}, {"timestamp": 1783255500, "price": 2.58}, {"timestamp": 1783256400, "price": 3.3}, {"timestamp": 1783257300, "price": 3.36}, {"timestamp": 1783258200, "price": 3.85}, {"timestamp": 1783259100, "price": 3.98}, {"timestamp": 1783260000, "price": 3.77}, {"timestamp": 1783260900, "price": 3.8}, {"timestamp": 1783261800, "price": 4.04}, {"timestamp": 1783262700, "price": 4.28}, {"timestamp": 1783263600, "price": 3.99}, {"timestamp": 1783264500, "price": 4.9}, {"timestamp": 1783265400, "price": 7.0}, {"timestamp": 1783266300, "price": 10.5}, {"timestamp": 1783267200, "price": 7.89}, {"timestamp": 1783268100, "price": 19.99}, {"timestamp": 1783269000, "price": 20.0}, {"timestamp": 1783269900, "price": 24.57}, {"timestamp": 1783270800, "price": 18.73}, {"timestamp": 1783271700, "price": 55.06}, {"timestamp": 1783272600, "price": 84.63}, {"timestamp": 1783273500, "price": 99.03}, {"timestamp": 1783274400, "price": 20.66}, {"timestamp": 1783275300, "price": 19.39}, {"timestamp": 1783276200, "price": 108.03}, {"timestamp": 1783277100, "price": 111.18}, {"timestamp": 1783278000, "price": 17.98}, {"timestamp": 1783278900, "price": 116.07}, {"timestamp": 1783279800, "price": 109.58}, {"timestamp": 1783280700, "price": 111.51}, {"timestamp": 1783281600, "price": 118.73}, {"timestamp": 1783282500, "price": 117.15}, {"timestamp": 1783283400, "price": 10.0}, {"timestamp": 1783284300, "price": 8.18}, {"timestamp": 1783285200, "price": 114.89}, {"timestamp": 1783286100, "price": 114.69}, {"timestamp": 1783287000, "price": 8.95}, {"timestamp": 1783287900, "price": 6.9}]