[{"timestamp": 1784505600, "price": 127.47}, {"timestamp": 1784506500, "price": 119.87}, {"timestamp": 1784507400, "price": 110.54}, {"timestamp": 1784508300, "price": 82.61}, {"timestamp": 1784509200, "price": 118.8}, {"timestamp": 1784510100, "price": 103.64}, {"timestamp": 1784511000, "price": 80.06}, {"timestamp": 1784511900, "price": 50.12}, {"timestamp": 1784512800, "price": 65.59}, {"timestamp": 1784513700, "price": 55.55}, {"timestamp": 1784514600, "price": 30.09}, {"timestamp": 1784515500, "price": 26.41}, {"timestamp": 1784516400, "price": 39.86}, {"timestamp": 1784517300, "price": 52.88}, {"timestamp": 1784518200, "price": 60.92}, {"timestamp": 1784519100, "price": 71.63}, {"timestamp": 1784520000, "price": 82.75}, {"timestamp": 1784520900, "price": 104.74}, {"timestamp": 1784521800, "price": 25.83}, {"timestamp": 1784522700, "price": 30.92}, {"timestamp": 1784523600, "price": 18.36}, {"timestamp": 1784524500, "price": 146.24}, {"timestamp": 1784525400, "price": 146.23}, {"timestamp": 1784526300, "price": 29.3}, {"timestamp": 1784527200, "price": 19.18}, {"timestamp": 1784528100, "price": 20.95}, {"timestamp": 1784529000, "price": 119.99}, {"timestamp": 1784529900, "price": 69.51}, {"timestamp": 1784530800, "price": 26.53}, {"timestamp": 1784531700, "price": 22.89}, {"timestamp": 1784532600, "price": 20.81}, {"timestamp": 1784533500, "price": 20.99}, {"timestamp": 1784534400, "price": 24.92}, {"timestamp": 1784535300, "price": 23.6}, {"timestamp": 1784536200, "price": 19.77}, {"timestamp": 1784537100, "price": 17.0}, {"timestamp": 1784538000, "price": 24.63}, {"timestamp": 1784538900, "price": 20.56}, {"timestamp": 1784539800, "price": 14.99}, {"timestamp": 1784540700, "price": 16.41}, {"timestamp": 1784541600, "price": 21.95}, {"timestamp": 1784542500, "price": 19.49}, {"timestamp": 1784543400, "price": 16.62}, {"timestamp": 1784544300, "price": 14.75}, {"timestamp": 1784545200, "price": 19.99}, {"timestamp": 1784546100, "price": 17.71}, {"timestamp": 1784547000, "price": 14.97}, {"timestamp": 1784547900, "price": 13.7}, {"timestamp": 1784548800, "price": 15.65}, {"timestamp": 1784549700, "price": 15.74}, {"timestamp": 1784550600, "price": 17.37}, {"timestamp": 1784551500, "price": 17.55}, {"timestamp": 1784552400, "price": 17.09}, {"timestamp": 1784553300, "price": 15.43}, {"timestamp": 1784554200, "price": 17.71}, {"timestamp": 1784555100, "price": 18.92}, {"timestamp": 1784556000, "price": 10.73}, {"timestamp": 1784556900, "price": 15.0}, {"timestamp": 1784557800, "price": 19.99}, {"timestamp": 1784558700, "price": 28.62}, {"timestamp": 1784559600, "price": 11.89}, {"timestamp": 1784560500, "price": 17.9}, {"timestamp": 1784561400, "price": 28.45}, {"timestamp": 1784562300, "price": 81.01}, {"timestamp": 1784563200, "price": 62.36}, {"timestamp": 1784564100, "price": 110.27}, {"timestamp": 1784565000, "price": 130.4}, {"timestamp": 1784565900, "price": 145.98}, {"timestamp": 1784566800, "price": 24.26}, {"timestamp": 1784567700, "price": 25.58}, {"timestamp": 1784568600, "price": 24.15}, {"timestamp": 1784569500, "price": 22.68}, {"timestamp": 1784570400, "price": 137.03}, {"timestamp": 1784571300, "price": 130.0}, {"timestamp": 1784572200, "price": 132.43}, {"timestamp": 1784573100, "price": 130.0}, {"timestamp": 1784574000, "price": 23.29}, {"timestamp": 1784574900, "price": 36.0}, {"timestamp": 1784575800, "price": 26.9}, {"timestamp": 1784576700, "price": 68.32}, {"timestamp": 1784577600, "price": 69.09}, {"timestamp": 1784578500, "price": 53.19}, {"timestamp": 1784579400, "price": 62.23}, {"timestamp": 1784580300, "price": 50.0}, {"timestamp": 1784581200, "price": 19.99}, {"timestamp": 1784582100, "price": 23.42}, {"timestamp": 1784583000, "price": 22.6}, {"timestamp": 1784583900, "price": 19.99}]