[{"timestamp": 1766448000, "price": 74.73}, {"timestamp": 1766448900, "price": 68.64}, {"timestamp": 1766449800, "price": 70.63}, {"timestamp": 1766450700, "price": 62.78}, {"timestamp": 1766451600, "price": 52.29}, {"timestamp": 1766452500, "price": 44.88}, {"timestamp": 1766453400, "price": 41.89}, {"timestamp": 1766454300, "price": 40.01}, {"timestamp": 1766455200, "price": 37.13}, {"timestamp": 1766456100, "price": 36.73}, {"timestamp": 1766457000, "price": 36.27}, {"timestamp": 1766457900, "price": 35.57}, {"timestamp": 1766458800, "price": 35.81}, {"timestamp": 1766459700, "price": 35.73}, {"timestamp": 1766460600, "price": 35.77}, {"timestamp": 1766461500, "price": 35.75}, {"timestamp": 1766462400, "price": 35.52}, {"timestamp": 1766463300, "price": 35.99}, {"timestamp": 1766464200, "price": 38.42}, {"timestamp": 1766465100, "price": 44.67}, {"timestamp": 1766466000, "price": 63.99}, {"timestamp": 1766466900, "price": 104.96}, {"timestamp": 1766467800, "price": 113.5}, {"timestamp": 1766468700, "price": 126.89}, {"timestamp": 1766469600, "price": 98.73}, {"timestamp": 1766470500, "price": 108.63}, {"timestamp": 1766471400, "price": 109.24}, {"timestamp": 1766472300, "price": 112.56}, {"timestamp": 1766473200, "price": 113.5}, {"timestamp": 1766474100, "price": 117.77}, {"timestamp": 1766475000, "price": 119.83}, {"timestamp": 1766475900, "price": 121.1}, {"timestamp": 1766476800, "price": 115.59}, {"timestamp": 1766477700, "price": 115.6}, {"timestamp": 1766478600, "price": 115.59}, {"timestamp": 1766479500, "price": 85.69}, {"timestamp": 1766480400, "price": 83.43}, {"timestamp": 1766481300, "price": 83.77}, {"timestamp": 1766482200, "price": 83.34}, {"timestamp": 1766483100, "price": 80.87}, {"timestamp": 1766484000, "price": 84.8}, {"timestamp": 1766484900, "price": 83.47}, {"timestamp": 1766485800, "price": 81.54}, {"timestamp": 1766486700, "price": 79.17}, {"timestamp": 1766487600, "price": 82.99}, {"timestamp": 1766488500, "price": 80.79}, {"timestamp": 1766489400, "price": 81.02}, {"timestamp": 1766490300, "price": 79.45}, {"timestamp": 1766491200, "price": 81.79}, {"timestamp": 1766492100, "price": 79.88}, {"timestamp": 1766493000, "price": 99.95}, {"timestamp": 1766493900, "price": 114.08}, {"timestamp": 1766494800, "price": 77.29}, {"timestamp": 1766495700, "price": 79.19}, {"timestamp": 1766496600, "price": 82.52}, {"timestamp": 1766497500, "price": 115.59}, {"timestamp": 1766498400, "price": 109.46}, {"timestamp": 1766499300, "price": 109.24}, {"timestamp": 1766500200, "price": 105.67}, {"timestamp": 1766501100, "price": 115.59}, {"timestamp": 1766502000, "price": 100.8}, {"timestamp": 1766502900, "price": 104.42}, {"timestamp": 1766503800, "price": 101.7}, {"timestamp": 1766504700, "price": 100.8}, {"timestamp": 1766505600, "price": 85.7}, {"timestamp": 1766506500, "price": 87.76}, {"timestamp": 1766507400, "price": 100.8}, {"timestamp": 1766508300, "price": 101.13}, {"timestamp": 1766509200, "price": 85.1}, {"timestamp": 1766510100, "price": 84.18}, {"timestamp": 1766511000, "price": 85.33}, {"timestamp": 1766511900, "price": 93.57}, {"timestamp": 1766512800, "price": 108.76}, {"timestamp": 1766513700, "price": 108.76}, {"timestamp": 1766514600, "price": 108.76}, {"timestamp": 1766515500, "price": 104.33}, {"timestamp": 1766516400, "price": 108.77}, {"timestamp": 1766517300, "price": 107.7}, {"timestamp": 1766518200, "price": 100.8}, {"timestamp": 1766519100, "price": 85.69}, {"timestamp": 1766520000, "price": 100.8}, {"timestamp": 1766520900, "price": 85.69}, {"timestamp": 1766521800, "price": 68.37}, {"timestamp": 1766522700, "price": 61.04}, {"timestamp": 1766523600, "price": 85.69}, {"timestamp": 1766524500, "price": 71.52}, {"timestamp": 1766525400, "price": 73.05}, {"timestamp": 1766526300, "price": 66.91}, {"timestamp": 1766527200, "price": 72.15}, {"timestamp": 1766528100, "price": 57.05}, {"timestamp": 1766529000, "price": 40.0}, {"timestamp": 1766529900, "price": 13.05}]