[{"timestamp": 1768867200, "price": 115.33}, {"timestamp": 1768868100, "price": 111.43}, {"timestamp": 1768869000, "price": 111.36}, {"timestamp": 1768869900, "price": 111.0}, {"timestamp": 1768870800, "price": 111.69}, {"timestamp": 1768871700, "price": 113.32}, {"timestamp": 1768872600, "price": 112.03}, {"timestamp": 1768873500, "price": 111.8}, {"timestamp": 1768874400, "price": 109.82}, {"timestamp": 1768875300, "price": 109.82}, {"timestamp": 1768876200, "price": 112.04}, {"timestamp": 1768877100, "price": 112.03}, {"timestamp": 1768878000, "price": 108.4}, {"timestamp": 1768878900, "price": 112.19}, {"timestamp": 1768879800, "price": 116.34}, {"timestamp": 1768880700, "price": 119.03}, {"timestamp": 1768881600, "price": 118.1}, {"timestamp": 1768882500, "price": 111.35}, {"timestamp": 1768883400, "price": 129.3}, {"timestamp": 1768884300, "price": 139.62}, {"timestamp": 1768885200, "price": 125.14}, {"timestamp": 1768886100, "price": 157.02}, {"timestamp": 1768887000, "price": 188.96}, {"timestamp": 1768887900, "price": 305.46}, {"timestamp": 1768888800, "price": 170.76}, {"timestamp": 1768889700, "price": 221.89}, {"timestamp": 1768890600, "price": 265.42}, {"timestamp": 1768891500, "price": 293.21}, {"timestamp": 1768892400, "price": 320.19}, {"timestamp": 1768893300, "price": 297.51}, {"timestamp": 1768894200, "price": 239.5}, {"timestamp": 1768895100, "price": 207.94}, {"timestamp": 1768896000, "price": 252.5}, {"timestamp": 1768896900, "price": 250.08}, {"timestamp": 1768897800, "price": 252.0}, {"timestamp": 1768898700, "price": 252.0}, {"timestamp": 1768899600, "price": 325.02}, {"timestamp": 1768900500, "price": 325.0}, {"timestamp": 1768901400, "price": 337.0}, {"timestamp": 1768902300, "price": 315.21}, {"timestamp": 1768903200, "price": 300.07}, {"timestamp": 1768904100, "price": 300.05}, {"timestamp": 1768905000, "price": 300.08}, {"timestamp": 1768905900, "price": 315.2}, {"timestamp": 1768906800, "price": 284.39}, {"timestamp": 1768907700, "price": 289.99}, {"timestamp": 1768908600, "price": 300.0}, {"timestamp": 1768909500, "price": 300.02}, {"timestamp": 1768910400, "price": 284.39}, {"timestamp": 1768911300, "price": 284.39}, {"timestamp": 1768912200, "price": 284.4}, {"timestamp": 1768913100, "price": 290.0}, {"timestamp": 1768914000, "price": 315.2}, {"timestamp": 1768914900, "price": 315.2}, {"timestamp": 1768915800, "price": 315.21}, {"timestamp": 1768916700, "price": 315.21}, {"timestamp": 1768917600, "price": 315.2}, {"timestamp": 1768918500, "price": 315.21}, {"timestamp": 1768919400, "price": 315.21}, {"timestamp": 1768920300, "price": 270.0}, {"timestamp": 1768921200, "price": 250.0}, {"timestamp": 1768922100, "price": 250.97}, {"timestamp": 1768923000, "price": 290.0}, {"timestamp": 1768923900, "price": 350.83}, {"timestamp": 1768924800, "price": 270.67}, {"timestamp": 1768925700, "price": 271.29}, {"timestamp": 1768926600, "price": 281.67}, {"timestamp": 1768927500, "price": 244.45}, {"timestamp": 1768928400, "price": 226.81}, {"timestamp": 1768929300, "price": 240.22}, {"timestamp": 1768930200, "price": 218.74}, {"timestamp": 1768931100, "price": 218.45}, {"timestamp": 1768932000, "price": 315.2}, {"timestamp": 1768932900, "price": 290.0}, {"timestamp": 1768933800, "price": 252.01}, {"timestamp": 1768934700, "price": 250.02}, {"timestamp": 1768935600, "price": 252.01}, {"timestamp": 1768936500, "price": 232.85}, {"timestamp": 1768937400, "price": 170.89}, {"timestamp": 1768938300, "price": 143.29}, {"timestamp": 1768939200, "price": 198.31}, {"timestamp": 1768940100, "price": 182.52}, {"timestamp": 1768941000, "price": 134.42}, {"timestamp": 1768941900, "price": 122.08}, {"timestamp": 1768942800, "price": 135.66}, {"timestamp": 1768943700, "price": 129.69}, {"timestamp": 1768944600, "price": 121.59}, {"timestamp": 1768945500, "price": 111.0}, {"timestamp": 1768946400, "price": 112.65}, {"timestamp": 1768947300, "price": 110.99}, {"timestamp": 1768948200, "price": 103.93}, {"timestamp": 1768949100, "price": 95.51}]